{
  "version": 3,
  "middleware": {
    "/": {
      "files": [
        "server/edge-runtime-webpack.js",
        "server/middleware.js"
      ],
      "name": "middleware",
      "page": "/",
      "matchers": [
        {
          "regexp": "^(?:\\/(_next\\/data\\/[^/]{1,}))?(?:\\/((?!api|_next\\/static|_next\\/image|_vercel|\\.well-known|favicon\\.ico|robots\\.txt|sitemap\\.xml|google[a-z0-9]+\\.html|.*\\.(?:png|jpg|jpeg|webp|svg|ico|css|js|woff2?|map|json)).*))(.json)?[\\/#\\?]?$",
          "originalSource": "/((?!api|_next/static|_next/image|_vercel|\\.well-known|favicon\\.ico|robots\\.txt|sitemap\\.xml|google[a-z0-9]+\\.html|.*\\.(?:png|jpg|jpeg|webp|svg|ico|css|js|woff2?|map|json)).*)"
        }
      ],
      "wasm": [],
      "assets": [],
      "env": {
        "__NEXT_BUILD_ID": "SJ2iC1iKRDoQANjiT19zY",
        "NEXT_SERVER_ACTIONS_ENCRYPTION_KEY": "urFRFm7X2R1GgwEpd/YJTvXxhmtTB4a9zR5siO4a5fM=",
        "__NEXT_PREVIEW_MODE_ID": "d995879ea4992791d6878706a2f3557f",
        "__NEXT_PREVIEW_MODE_ENCRYPTION_KEY": "1021ddb7c70bb693d21b0419a29dc0c1b1586756c3786e0f6d0ac76973969d63",
        "__NEXT_PREVIEW_MODE_SIGNING_KEY": "1dc37da3c6b9b29acac33b921fe6d34a818403802e6210d9560b49dddf7987cd"
      }
    }
  },
  "functions": {},
  "sortedMiddleware": [
    "/"
  ]
}