{
  "version": 3,
  "middleware": {
    "/": {
      "files": [
        "server/edge-runtime-webpack.js",
        "server/middleware.js"
      ],
      "name": "middleware",
      "page": "/",
      "matchers": [
        {
          "regexp": "^(?:\\/(_next\\/data\\/[^/]{1,}))?(?:\\/((?!api|_next\\/static|_next\\/image|_vercel|\\.well-known|favicon\\.ico|robots\\.txt|sitemap\\.xml|google[a-z0-9]+\\.html|.*\\.(?:png|jpg|jpeg|webp|svg|ico|css|js|woff2?|map|json)).*))(.json)?[\\/#\\?]?$",
          "originalSource": "/((?!api|_next/static|_next/image|_vercel|\\.well-known|favicon\\.ico|robots\\.txt|sitemap\\.xml|google[a-z0-9]+\\.html|.*\\.(?:png|jpg|jpeg|webp|svg|ico|css|js|woff2?|map|json)).*)"
        }
      ],
      "wasm": [],
      "assets": [],
      "env": {
        "__NEXT_BUILD_ID": "YB0ZVboaSPW9iuVfv5xqn",
        "NEXT_SERVER_ACTIONS_ENCRYPTION_KEY": "8Kr+p6tTJYEoI9cxIDCwO3SqY19iTWhnDq3aVJxsmZI=",
        "__NEXT_PREVIEW_MODE_ID": "fcde79ab9b9ce10a5a119a79ea69993d",
        "__NEXT_PREVIEW_MODE_ENCRYPTION_KEY": "724241b2abdeb9aa9b2adeadf06adbd73a2a9b4a532256e101b39777521be333",
        "__NEXT_PREVIEW_MODE_SIGNING_KEY": "2e3c2a92f190f014b562bf2ce2c2ac987c924e86906547dd5a6642f40cefced2"
      }
    }
  },
  "functions": {},
  "sortedMiddleware": [
    "/"
  ]
}