{
  "version": 3,
  "middleware": {
    "/": {
      "files": [
        "server/edge-runtime-webpack.js",
        "server/middleware.js"
      ],
      "name": "middleware",
      "page": "/",
      "matchers": [
        {
          "regexp": "^(?:\\/(_next\\/data\\/[^/]{1,}))?(?:\\/((?!api|_next\\/static|_next\\/image|_vercel|\\.well-known|favicon\\.ico|robots\\.txt|sitemap\\.xml|google[a-z0-9]+\\.html|.*\\.(?:png|jpg|jpeg|webp|svg|ico|css|js|woff2?|map|json)).*))(.json)?[\\/#\\?]?$",
          "originalSource": "/((?!api|_next/static|_next/image|_vercel|\\.well-known|favicon\\.ico|robots\\.txt|sitemap\\.xml|google[a-z0-9]+\\.html|.*\\.(?:png|jpg|jpeg|webp|svg|ico|css|js|woff2?|map|json)).*)"
        }
      ],
      "wasm": [],
      "assets": [],
      "env": {
        "__NEXT_BUILD_ID": "MAJOHBYz_xNM49wEzhZ_1",
        "NEXT_SERVER_ACTIONS_ENCRYPTION_KEY": "i8Uh3fYYx4VlrLZTIi0yppnKMmDk6LvT80jRVInyWCY=",
        "__NEXT_PREVIEW_MODE_ID": "be6336d8823029acff1a2fc8fd143b8b",
        "__NEXT_PREVIEW_MODE_ENCRYPTION_KEY": "8b0f11dae0c04e6280e6382eccc6ebc4b66bf1250efa8d38923b7a8b96042e66",
        "__NEXT_PREVIEW_MODE_SIGNING_KEY": "6c35959af9140d47769a4331dc1141ff7b4a3bda2a948da56875eab98e371462"
      }
    }
  },
  "functions": {},
  "sortedMiddleware": [
    "/"
  ]
}